[
    { "id": 1, "name": "El Tren Magico", "icon": "assets/sprites/POVs/pov1.png", "transition": "assets/sprites/Transitions/transition_pov1.png", "isTheOne": false },
    { "id": 2, "name": "GloboVision", "icon": "assets/sprites/POVs/pov2.png", "transition": "assets/sprites/Transitions/transition_pov2.png", "isTheOne": false },
    { "id": 3, "name": "La Nacion Mostaza", "icon": "assets/sprites/POVs/pov3.png", "transition": "assets/sprites/Transitions/transition_pov3.png", "isTheOne": false },
    { "id": 4, "name": "Osito Willy", "icon": "assets/sprites/POVs/pov4.png", "transition": "assets/sprites/Transitions/transition_pov4.png", "isTheOne": false },
    { "id": 5, "name": "Orden y Progreso", "icon": "assets/sprites/POVs/pov5.png", "transition": "assets/sprites/Transitions/transition_pov5.png", "isTheOne": false },
    { "id": 6, "name": "Dele Dele!", "icon": "assets/sprites/POVs/pov6.png", "transition": "assets/sprites/Transitions/transition_pov6.png", "isTheOne": false },
    { "id": 7, "name": "City Tour", "icon": "assets/sprites/POVs/pov7.png", "transition": "assets/sprites/Transitions/transition_pov7.png", "isTheOne": false },
    { "id": 8, "name": "Valaparaiso de mi Amor", "icon": "assets/sprites/POVs/pov8.png", "transition": "assets/sprites/Transitions/transition_pov8.png", "isTheOne": false },
    { "id": 9, "name": "Aseo y Ornato", "icon": "assets/sprites/POVs/pov9.png", "transition": "assets/sprites/Transitions/transition_pov9.png", "isTheOne": false },
    { "id": 10, "name": "Kiltro", "icon": "assets/sprites/POVs/pov10.png", "transition": "assets/sprites/Transitions/transition_pov10.png", "isTheOne": false },
    { "id": 11, "name": "Arriba en la Cordillera", "icon": "assets/sprites/POVs/pov11.png", "transition": "assets/sprites/Transitions/transition_pov11.png", "isTheOne": false },
    { "id": 12, "name": "Nubosidad Parcial", "icon": "assets/sprites/POVs/pov12.png", "transition": "assets/sprites/Transitions/transition_pov12.png", "isTheOne": false },
    { "id": 13, "name": "Se va enredando, enredando", "icon": "assets/sprites/POVs/pov13.png", "transition": "assets/sprites/Transitions/transition_pov13.png", "isTheOne": false },
    { "id": 14, "name": "El Jardin Gigante", "icon": "assets/sprites/POVs/pov14.png", "transition": "assets/sprites/Transitions/transition_pov14.png", "isTheOne": false },
    { "id": 15, "name": "Buque Esmeralda", "icon": "assets/sprites/POVs/pov15.png", "transition": "assets/sprites/Transitions/transition_pov15.png", "isTheOne": false },
    { "id": 16, "name": "Tren al Sur", "icon": "assets/sprites/POVs/pov16.png", "transition": "assets/sprites/Transitions/transition_pov16.png", "isTheOne": false }
  ]